bartocsuggest/__init__.py
bartocsuggest/jskos.py
bartocsuggest/utility.py
bartocsuggest-0.0.3.dist-info/METADATA
bartocsuggest-0.0.3.dist-info/WHEEL
bartocsuggest-0.0.3.dist-info/top_level.txt
bartocsuggest-0.0.3.dist-info/RECORD
