Metadata-Version: 2.1
Name: bartocsuggest
Version: 0.0.3
Summary: Vocabulary suggestion module based on BARTOC FAST
Home-page: https://github.com/MHindermann/bartocsuggest
Author: Maximilian Hindermann
Author-email: maximilian.hindermann@unibas.ch
License: UNKNOWN
Platform: UNKNOWN
Classifier: Programming Language :: Python :: 3
Classifier: License :: OSI Approved :: MIT License
Classifier: Operating System :: OS Independent
Requires-Python: >=3.7
Requires-Dist: urllib3
Requires-Dist: requests
Requires-Dist: python-Levenshtein-wheels
Requires-Dist: openpyxl
Requires-Dist: annif-client
